[
  {
    "url": "https://www.autotrader.ca/offers/honda-hr-v-ex-black-gasoline-black-84e95cb9-8311-4962-8c62-5e2954e33e14",
    "v_make": "Honda",
    "raw_make": "Honda",
    "v_model": "HR-V",
    "raw_model": "HR-V",
    "v_year": 2018,
    "raw_year": 2018,
    "price_public_raw": 21988,
    "price_dealer_raw": 21988,
    "tracking_price": 21988,
    "v_mileageRaw": 70219,
    "raw_mileageRaw": 70219,
    "tracking_mileage": 70219,
    "seller_type": "Dealer",
    "seller_isDealer": true,
    "seller_name": "Richmond Hyundai",
    "v_vin": "3CZRU6H52JM107249",
    "v_modelVersion": "EX Black",
    "raw_modelVersion": "EX Black",
    "v_bodyColor": "Black",
    "v_bodyColorOrig": "Crystal Black Pearl",
    "v_fuel": "Gasoline",
    "v_transmission": "Automatic",
    "v_upholstery": null,
    "images_count": 25,
    "image0": "https://prod.pictures.autoscout24.net/listing-images/84e95cb9-8311-4962-8c62-5e2954e33e14_6bad889d-2959-4234-b690-1737fb02615d.jpg/1280x960.webp",
    "headerImage": "https://prod.pictures.autoscout24.net/listing-images/84e95cb9-8311-4962-8c62-5e2954e33e14_6bad889d-2959-4234-b690-1737fb02615d.jpg/120x90.webp",
    "carfax_url": "https://vhr.carfax.ca/?id=HzLf/dHl/wV0muL1/19ZkQL7FfHPEdZf",
    "carfax_avail": true,
    "wltp_city_raw": 8.9,
    "wltp_hwy_raw": 7.5,
    "comfort_items": [
      "Air conditioning",
      "Automatic climate control",
      "Cruise control",
      "Power windows",
      "Remote Keyless Entry",
      "Steering Wheel Audio Controls"
    ],
    "safety_items": [
      "Alarm system",
      "Daytime running lights",
      "Driver-side airbag",
      "Electronic stability control",
      "Fog lights",
      "Passenger-side airbag",
      "Power Door Locks",
      "Power steering",
      "Traction control"
    ],
    "v_comfort": [
      "Air conditioning",
      "Automatic climate control",
      "Cruise control",
      "Power windows",
      "Remote Keyless Entry",
      "Steering Wheel Audio Controls"
    ],
    "v_safety": [
      "Alarm system",
      "Daytime running lights",
      "Driver-side airbag",
      "Electronic stability control",
      "Fog lights",
      "Passenger-side airbag",
      "Power Door Locks",
      "Power steering",
      "Traction control"
    ],
    "priceEval": 1,
    "evalRanges": true,
    "crossRefId": "69342337",
    "uuid": "84e95cb9-8311-4962-8c62-5e2954e33e14",
    "extCustId": "20181218135614272",
    "city": "Richmond",
    "province": "BC"
  },
  {
    "url": "https://www.autotrader.ca/offers/subaru-forester-2-5i-premier-carplay-cuir-toit-ouvrant-gasoline-grey-e5eb1c9f-19ae-4318-a05a-7ae2a7f2e6be",
    "v_make": "Subaru",
    "raw_make": "Subaru",
    "v_model": "Forester",
    "raw_model": "Forester",
    "v_year": 2020,
    "raw_year": 2020,
    "price_public_raw": 26770,
    "price_dealer_raw": 26770,
    "tracking_price": 26770,
    "v_mileageRaw": 54760,
    "raw_mileageRaw": 54760,
    "tracking_mileage": 54760,
    "seller_type": "Dealer",
    "seller_isDealer": true,
    "seller_name": "Subaru Rive-Nord",
    "v_vin": "JF2SKEXC9LH539112",
    "v_modelVersion": "2.5i Premier CARPLAY+CUIR+TOIT.OUVRANT",
    "raw_modelVersion": "2.5i Premier CARPLAY+CUIR+TOIT.OUVRANT",
    "v_bodyColor": "Grey",
    "v_bodyColorOrig": "Magnetite Grey Metallic",
    "v_fuel": "Gasoline",
    "v_transmission": "Automatic",
    "v_upholstery": "Brown",
    "images_count": 46,
    "image0": "https://prod.pictures.autoscout24.net/listing-images/e5eb1c9f-19ae-4318-a05a-7ae2a7f2e6be_ff163d3f-5ef1-4866-999c-68385880953a.jpg/1280x960.webp",
    "headerImage": "https://prod.pictures.autoscout24.net/listing-images/e5eb1c9f-19ae-4318-a05a-7ae2a7f2e6be_ff163d3f-5ef1-4866-999c-68385880953a.jpg/120x90.webp",
    "carfax_url": "",
    "carfax_avail": true,
    "wltp_city_raw": 9,
    "wltp_hwy_raw": 7.2,
    "comfort_items": [
      "Cruise control",
      "Heated Seats",
      "Panoramic Roof",
      "Power Mirrors",
      "Power windows",
      "Sun/Moonroof",
      "Tinted windows"
    ],
    "safety_items": [
      "Electronic stability control",
      "Fog lights"
    ],
    "v_comfort": [
      "Cruise control",
      "Heated Seats",
      "Panoramic Roof",
      "Power Mirrors",
      "Power windows",
      "Sun/Moonroof",
      "Tinted windows"
    ],
    "v_safety": [
      "Electronic stability control",
      "Fog lights"
    ],
    "priceEval": 1,
    "evalRanges": true,
    "crossRefId": "68607428",
    "uuid": "e5eb1c9f-19ae-4318-a05a-7ae2a7f2e6be",
    "extCustId": "20100601124454920",
    "city": "Boisbriand",
    "province": "QC"
  },
  {
    "url": "https://www.autotrader.ca/offers/subaru-forester-limited-gasoline-grey-e0425de0-aaa1-4884-95ce-19b64085c81a",
    "v_make": "Subaru",
    "raw_make": "Subaru",
    "v_model": "Forester",
    "raw_model": "Forester",
    "v_year": 2025,
    "raw_year": 2025,
    "price_public_raw": 42061,
    "price_dealer_raw": 42061,
    "tracking_price": 42061,
    "v_mileageRaw": 8800,
    "raw_mileageRaw": 8800,
    "tracking_mileage": 8800,
    "seller_type": "Dealer",
    "seller_isDealer": true,
    "seller_name": "Subaru de Laval",
    "v_vin": "JF2SLDRC5SH563152",
    "v_modelVersion": "Limited",
    "raw_modelVersion": "Limited",
    "v_bodyColor": "Grey",
    "v_bodyColorOrig": null,
    "v_fuel": "Gasoline",
    "v_transmission": "Automatic",
    "v_upholstery": "Black",
    "images_count": 19,
    "image0": "https://prod.pictures.autoscout24.net/listing-images/e0425de0-aaa1-4884-95ce-19b64085c81a_b91f2c45-e061-4826-b275-6e179cd39f51.jpg/1280x960.webp",
    "headerImage": "https://prod.pictures.autoscout24.net/listing-images/e0425de0-aaa1-4884-95ce-19b64085c81a_b91f2c45-e061-4826-b275-6e179cd39f51.jpg/120x90.webp",
    "carfax_url": "",
    "carfax_avail": true,
    "wltp_city_raw": 9.1,
    "wltp_hwy_raw": 7.2,
    "comfort_items": [
      "Cruise control",
      "Heated steering wheel",
      "Navigation system",
      "Panoramic Roof"
    ],
    "safety_items": [
      "Alarm system",
      "Driver-side airbag",
      "Electronic stability control",
      "Fog lights",
      "Passenger-side airbag",
      "Power steering"
    ],
    "v_comfort": [
      "Cruise control",
      "Heated steering wheel",
      "Navigation system",
      "Panoramic Roof"
    ],
    "v_safety": [
      "Alarm system",
      "Driver-side airbag",
      "Electronic stability control",
      "Fog lights",
      "Passenger-side airbag",
      "Power steering"
    ],
    "priceEval": 1,
    "evalRanges": true,
    "crossRefId": "69709828",
    "uuid": "e0425de0-aaa1-4884-95ce-19b64085c81a",
    "extCustId": "200441413274706",
    "city": "Laval",
    "province": "QC"
  },
  {
    "url": "https://www.autotrader.ca/offers/honda-hr-v-sport-4wd-low-mileage--dilawri-certified-gasoline-white-f3080c7c-52e7-4de7-a1d8-5d7347b404ba",
    "v_make": "Honda",
    "raw_make": "Honda",
    "v_model": "HR-V",
    "raw_model": "HR-V",
    "v_year": 2022,
    "raw_year": 2022,
    "price_public_raw": 26888,
    "price_dealer_raw": 26888,
    "tracking_price": 26888,
    "v_mileageRaw": 38451,
    "raw_mileageRaw": 38451,
    "tracking_mileage": 38451,
    "seller_type": "Dealer",
    "seller_isDealer": true,
    "seller_name": "North Shore Honda",
    "v_vin": "3CZRU6H20NM101574",
    "v_modelVersion": "Sport 4WD [Low Mileage | Dilawri Certified]",
    "raw_modelVersion": "Sport 4WD [Low Mileage | Dilawri Certified]",
    "v_bodyColor": "White",
    "v_bodyColorOrig": "Platinum White Pearl",
    "v_fuel": "Gasoline",
    "v_transmission": "Automatic",
    "v_upholstery": "Black",
    "images_count": 32,
    "image0": "https://prod.pictures.autoscout24.net/listing-images/f3080c7c-52e7-4de7-a1d8-5d7347b404ba_7038a81f-d671-4c08-94ff-5c357fe36cde.jpg/1280x960.webp",
    "headerImage": "https://prod.pictures.autoscout24.net/listing-images/f3080c7c-52e7-4de7-a1d8-5d7347b404ba_7038a81f-d671-4c08-94ff-5c357fe36cde.jpg/120x90.webp",
    "carfax_url": "https://vhr.carfax.ca/?id=2HLQJ5qPK4ZunjTKuVFhDrG3M5vfxuwa",
    "carfax_avail": true,
    "wltp_city_raw": 9.1,
    "wltp_hwy_raw": 7.7,
    "comfort_items": [
      "Automatic climate control",
      "Cruise control",
      "Leather steering wheel",
      "Power windows",
      "Remote Keyless Entry",
      "Steering Wheel Audio Controls"
    ],
    "safety_items": [
      "Adaptive Cruise Control",
      "Alarm system",
      "Daytime running lights",
      "Driver-side airbag",
      "Electronic stability control",
      "Fog lights",
      "Lane departure warning system",
      "Passenger-side airbag",
      "Power Door Locks",
      "Power steering",
      "Traction control"
    ],
    "v_comfort": [
      "Automatic climate control",
      "Cruise control",
      "Leather steering wheel",
      "Power windows",
      "Remote Keyless Entry",
      "Steering Wheel Audio Controls"
    ],
    "v_safety": [
      "Adaptive Cruise Control",
      "Alarm system",
      "Daytime running lights",
      "Driver-side airbag",
      "Electronic stability control",
      "Fog lights",
      "Lane departure warning system",
      "Passenger-side airbag",
      "Power Door Locks",
      "Power steering",
      "Traction control"
    ],
    "priceEval": 1,
    "evalRanges": true,
    "crossRefId": "69493413",
    "uuid": "f3080c7c-52e7-4de7-a1d8-5d7347b404ba",
    "extCustId": "BS20051129101427",
    "city": "North Vancouver",
    "province": "BC"
  },
  {
    "url": "https://www.autotrader.ca/offers/subaru-forester-touring-awd-auto-ac-toit-gr-elect-mags-camera-recu-gasoline-black-9aa872bb-c4d5-47f8-a30c-edfa777e87e5",
    "v_make": "Subaru",
    "raw_make": "Subaru",
    "v_model": "Forester",
    "raw_model": "Forester",
    "v_year": 2024,
    "raw_year": 2024,
    "price_public_raw": 28598,
    "price_dealer_raw": 28598,
    "tracking_price": 28598,
    "v_mileageRaw": 124335,
    "raw_mileageRaw": 124335,
    "tracking_mileage": 124335,
    "seller_type": "Dealer",
    "seller_isDealer": true,
    "seller_name": "HGrégoire Carignan",
    "v_vin": "JF2SKEDC0RH442118",
    "v_modelVersion": "Touring AWD AUTO AC TOIT GR ELECT MAGS CAMERA RECU",
    "raw_modelVersion": "Touring AWD AUTO AC TOIT GR ELECT MAGS CAMERA RECU",
    "v_bodyColor": "Black",
    "v_bodyColorOrig": "Crystal Black Silica",
    "v_fuel": "Gasoline",
    "v_transmission": "Automatic",
    "v_upholstery": "Black",
    "images_count": 28,
    "image0": "https://prod.pictures.autoscout24.net/listing-images/9aa872bb-c4d5-47f8-a30c-edfa777e87e5_31845cba-a8eb-4363-8e03-40578d37259b.jpg/1280x960.webp",
    "headerImage": "https://prod.pictures.autoscout24.net/listing-images/9aa872bb-c4d5-47f8-a30c-edfa777e87e5_31845cba-a8eb-4363-8e03-40578d37259b.jpg/120x90.webp",
    "carfax_url": "",
    "carfax_avail": true,
    "wltp_city_raw": 9,
    "wltp_hwy_raw": 7.2,
    "comfort_items": [
      "Air conditioning",
      "Automatic Climate Control, Dual-Zone",
      "Cruise control",
      "Heated Seats",
      "Panoramic Roof",
      "Park Distance Control",
      "Parking Assist Rear Sensors",
      "Power Mirrors",
      "Power Seats",
      "Power windows",
      "Sun/Moonroof",
      "Tinted windows"
    ],
    "safety_items": [
      "Anti-lock braking system (ABS)",
      "Fog lights",
      "Power Door Locks",
      "Traction control"
    ],
    "v_comfort": [
      "Air conditioning",
      "Automatic Climate Control, Dual-Zone",
      "Cruise control",
      "Heated Seats",
      "Panoramic Roof",
      "Park Distance Control",
      "Parking Assist Rear Sensors",
      "Power Mirrors",
      "Power Seats",
      "Power windows",
      "Sun/Moonroof",
      "Tinted windows"
    ],
    "v_safety": [
      "Anti-lock braking system (ABS)",
      "Fog lights",
      "Power Door Locks",
      "Traction control"
    ],
    "priceEval": 2,
    "evalRanges": true,
    "crossRefId": "69340765",
    "uuid": "9aa872bb-c4d5-47f8-a30c-edfa777e87e5",
    "extCustId": "2005428142959706",
    "city": "Carignan",
    "province": "QC"
  },
  {
    "url": "https://www.autotrader.ca/offers/subaru-forester-2-5i-limited-w-gasoline-grey-b2d3d634-e05f-4cc2-a643-b5f7bac79a89",
    "v_make": "Subaru",
    "raw_make": "Subaru",
    "v_model": "Forester",
    "raw_model": "Forester",
    "v_year": 2019,
    "raw_year": 2019,
    "price_public_raw": 25111,
    "price_dealer_raw": 25111,
    "tracking_price": 25111,
    "v_mileageRaw": 72880,
    "raw_mileageRaw": 72880,
    "tracking_mileage": 72880,
    "seller_type": "Dealer",
    "seller_isDealer": true,
    "seller_name": "Subaru Rive-Nord",
    "v_vin": "JF2SKEUC2KH567448",
    "v_modelVersion": "2.5I LIMITED W",
    "raw_modelVersion": "2.5I LIMITED W",
    "v_bodyColor": "Grey",
    "v_bodyColorOrig": "Dark Grey Metallic",
    "v_fuel": "Gasoline",
    "v_transmission": "Automatic",
    "v_upholstery": "Grey",
    "images_count": 50,
    "image0": "https://prod.pictures.autoscout24.net/listing-images/b2d3d634-e05f-4cc2-a643-b5f7bac79a89_2ae1f0a8-7765-4c33-a3c3-9988846d11c7.jpg/1280x960.webp",
    "headerImage": "https://prod.pictures.autoscout24.net/listing-images/b2d3d634-e05f-4cc2-a643-b5f7bac79a89_2ae1f0a8-7765-4c33-a3c3-9988846d11c7.jpg/120x90.webp",
    "carfax_url": "",
    "carfax_avail": true,
    "wltp_city_raw": 9,
    "wltp_hwy_raw": 7.2,
    "comfort_items": [
      "Cruise control",
      "Heated Seats",
      "Panoramic Roof",
      "Power Mirrors",
      "Power windows",
      "Sun/Moonroof",
      "Tinted windows"
    ],
    "safety_items": [
      "Electronic stability control",
      "Fog lights"
    ],
    "v_comfort": [
      "Cruise control",
      "Heated Seats",
      "Panoramic Roof",
      "Power Mirrors",
      "Power windows",
      "Sun/Moonroof",
      "Tinted windows"
    ],
    "v_safety": [
      "Electronic stability control",
      "Fog lights"
    ],
    "priceEval": 2,
    "evalRanges": true,
    "crossRefId": "69225441",
    "uuid": "b2d3d634-e05f-4cc2-a643-b5f7bac79a89",
    "extCustId": "20100601124454920",
    "city": "Boisbriand",
    "province": "QC"
  },
  {
    "url": "https://www.autotrader.ca/offers/subaru-forester-sport-eyesight-cvt-awd-gasoline-black-ce75d843-2f6d-4b19-92f9-718f9f3d8745",
    "v_make": "Subaru",
    "raw_make": "Subaru",
    "v_model": "Forester",
    "raw_model": "Forester",
    "v_year": 2022,
    "raw_year": 2022,
    "price_public_raw": 29921,
    "price_dealer_raw": 29921,
    "tracking_price": 29921,
    "v_mileageRaw": 54481,
    "raw_mileageRaw": 54481,
    "tracking_mileage": 54481,
    "seller_type": "Dealer",
    "seller_isDealer": true,
    "seller_name": "Subaru Montreal",
    "v_vin": "JF2SKEHC6NH472616",
    "v_modelVersion": "Sport Eyesight CVT AWD",
    "raw_modelVersion": "Sport Eyesight CVT AWD",
    "v_bodyColor": "Black",
    "v_bodyColorOrig": "Crystal Black Silica",
    "v_fuel": "Gasoline",
    "v_transmission": "Automatic",
    "v_upholstery": null,
    "images_count": 6,
    "image0": "https://prod.pictures.autoscout24.net/listing-images/ce75d843-2f6d-4b19-92f9-718f9f3d8745_d64bdbda-dfa9-4829-998c-098278093369.jpg/1280x960.webp",
    "headerImage": "https://prod.pictures.autoscout24.net/listing-images/ce75d843-2f6d-4b19-92f9-718f9f3d8745_d64bdbda-dfa9-4829-998c-098278093369.jpg/120x90.webp",
    "carfax_url": "",
    "carfax_avail": true,
    "wltp_city_raw": 9,
    "wltp_hwy_raw": 7.2,
    "comfort_items": [],
    "safety_items": [],
    "v_comfort": [],
    "v_safety": [],
    "priceEval": 2,
    "evalRanges": true,
    "crossRefId": "69791307",
    "uuid": "ce75d843-2f6d-4b19-92f9-718f9f3d8745",
    "extCustId": "20121022145200018",
    "city": "Montreal",
    "province": "QC"
  },
  {
    "url": "https://www.autotrader.ca/offers/subaru-forester-awd--clean-carfax--1-owner--alloy-wheels--cam-gasoline-b54e2bb0-abce-4925-8efe-3b1c1c0a9bb8",
    "v_make": "Subaru",
    "raw_make": "Subaru",
    "v_model": "Forester",
    "raw_model": "Forester",
    "v_year": 2025,
    "raw_year": 2025,
    "price_public_raw": 33888,
    "price_dealer_raw": 33888,
    "tracking_price": 33888,
    "v_mileageRaw": 21864,
    "raw_mileageRaw": 21864,
    "tracking_mileage": 21864,
    "seller_type": "Dealer",
    "seller_isDealer": true,
    "seller_name": "SUBARU OF MISSISSAUGA",
    "v_vin": "JF2SLDAC3SH440199",
    "v_modelVersion": "AWD | CLEAN CARFAX | 1 OWNER |  ALLOY WHEELS | CAM",
    "raw_modelVersion": "AWD | CLEAN CARFAX | 1 OWNER |  ALLOY WHEELS | CAM",
    "v_bodyColor": null,
    "v_bodyColorOrig": null,
    "v_fuel": "Gasoline",
    "v_transmission": "Automatic",
    "v_upholstery": null,
    "images_count": 14,
    "image0": "https://prod.pictures.autoscout24.net/listing-images/b54e2bb0-abce-4925-8efe-3b1c1c0a9bb8_7b839632-f3d1-4a58-92a7-6a84df970c9c.jpg/1280x960.webp",
    "headerImage": "https://prod.pictures.autoscout24.net/listing-images/b54e2bb0-abce-4925-8efe-3b1c1c0a9bb8_7b839632-f3d1-4a58-92a7-6a84df970c9c.jpg/120x90.webp",
    "carfax_url": "https://vhr.carfax.ca/?id=/JxfhIf9WDWUjttDYCsGZoxcCP7aSGw1",
    "carfax_avail": true,
    "wltp_city_raw": 9.1,
    "wltp_hwy_raw": 7.2,
    "comfort_items": [],
    "safety_items": [],
    "v_comfort": [],
    "v_safety": [],
    "priceEval": 1,
    "evalRanges": true,
    "crossRefId": "69736934",
    "uuid": "b54e2bb0-abce-4925-8efe-3b1c1c0a9bb8",
    "extCustId": "ON20071119114440811",
    "city": "Mississauga",
    "province": "ON"
  },
  {
    "url": "https://www.autotrader.ca/offers/honda-hr-v-sport-awd-heated-wheel-sunroof-remote-start-gasoline-black-f0118488-a145-46a6-b94b-26d99e465b23",
    "v_make": "Honda",
    "raw_make": "Honda",
    "v_model": "HR-V",
    "raw_model": "HR-V",
    "v_year": 2023,
    "raw_year": 2023,
    "price_public_raw": 29894,
    "price_dealer_raw": 29894,
    "tracking_price": 29894,
    "v_mileageRaw": 91523,
    "raw_mileageRaw": 91523,
    "tracking_mileage": 91523,
    "seller_type": "Dealer",
    "seller_isDealer": true,
    "seller_name": "Carlton Honda",
    "v_vin": "3CZRZ2H53PM100152",
    "v_modelVersion": "Sport AWD HEATED WHEEL SUNROOF REMOTE START",
    "raw_modelVersion": "Sport AWD HEATED WHEEL SUNROOF REMOTE START",
    "v_bodyColor": "Black",
    "v_bodyColorOrig": "Crystal Black Pearl",
    "v_fuel": "Gasoline",
    "v_transmission": "Automatic",
    "v_upholstery": "Black",
    "images_count": 18,
    "image0": "https://prod.pictures.autoscout24.net/listing-images/f0118488-a145-46a6-b94b-26d99e465b23_e49a426b-32a4-48c6-a172-b7cb22150094.jpg/1280x960.webp",
    "headerImage": "https://prod.pictures.autoscout24.net/listing-images/f0118488-a145-46a6-b94b-26d99e465b23_e49a426b-32a4-48c6-a172-b7cb22150094.jpg/120x90.webp",
    "carfax_url": "",
    "carfax_avail": true,
    "wltp_city_raw": 9.4,
    "wltp_hwy_raw": 7.8,
    "comfort_items": [],
    "safety_items": [],
    "v_comfort": [],
    "v_safety": [],
    "priceEval": 1,
    "evalRanges": true,
    "crossRefId": "69297772",
    "uuid": "f0118488-a145-46a6-b94b-26d99e465b23",
    "extCustId": "20171219213045628",
    "city": "Prince Albert",
    "province": "SK"
  }
]